Metadata-Version: 1.1
Name: agglo-tt
Version: 1.2.1
Summary: Library of unit tests above pytest
Home-page: http://sourceforge.net/projects/agglo/
Author: toubab1
Author-email: eti.laurent@gmail.com
License: GPL/Proprietary
Platform: UNKNOWN
Classifier: Programming Language :: Python
Classifier: Development Status :: 3 - Alpha
Classifier: Natural Language :: French
Classifier: Operating System :: OS Independent
Classifier: Programming Language :: Python :: 2.7
Classifier: Topic :: Software Development
